odoo/addons/l10n_it_partner_statement_riba/README.rst
odoo/addons/l10n_it_partner_statement_riba/__init__.py
odoo/addons/l10n_it_partner_statement_riba/__manifest__.py
odoo/addons/l10n_it_partner_statement_riba/i18n/it.po
odoo/addons/l10n_it_partner_statement_riba/i18n/l10n_it_partner_statement_riba.pot
odoo/addons/l10n_it_partner_statement_riba/readme/CONTRIBUTORS.rst
odoo/addons/l10n_it_partner_statement_riba/readme/DESCRIPTION.rst
odoo/addons/l10n_it_partner_statement_riba/reports/__init__.py
odoo/addons/l10n_it_partner_statement_riba/reports/outstanding_statement.py
odoo/addons/l10n_it_partner_statement_riba/reports/outstanding_statement.xml
odoo/addons/l10n_it_partner_statement_riba/reports/outstanding_statement_xlsx.py
odoo/addons/l10n_it_partner_statement_riba/static/description/icon.png
odoo/addons/l10n_it_partner_statement_riba/static/description/index.html
odoo/addons/l10n_it_partner_statement_riba/tests/__init__.py
odoo/addons/l10n_it_partner_statement_riba/tests/test_outstanding_statement.py
odoo/addons/l10n_it_partner_statement_riba/wizards/__init__.py
odoo/addons/l10n_it_partner_statement_riba/wizards/outstanding_statement.py
odoo/addons/l10n_it_partner_statement_riba/wizards/outstanding_statement_views.xml
odoo14_addon_l10n_it_partner_statement_riba-14.0.1.1.0.dist-info/METADATA
odoo14_addon_l10n_it_partner_statement_riba-14.0.1.1.0.dist-info/WHEEL
odoo14_addon_l10n_it_partner_statement_riba-14.0.1.1.0.dist-info/top_level.txt
odoo14_addon_l10n_it_partner_statement_riba-14.0.1.1.0.dist-info/RECORD
