Metadata-Version: 2.1
Name: odoo14-addon-l10n_it_partner_statement_riba
Version: 14.0.1.1.0
Summary: Visualizzare le RiBa negli estratti conto cliente.
Home-page: https://github.com/OCA/l10n-italy
Author: PyTech, Odoo Community Association (OCA)
Author-email: support@odoo-community.org
License: AGPL-3
Classifier: Programming Language :: Python
Classifier: Framework :: Odoo
Classifier: Framework :: Odoo :: 14.0
Classifier: License :: OSI Approved :: GNU Affero General Public License v3
Requires-Python: >=3.6
Requires-Dist: odoo14-addon-l10n-it-ricevute-bancarie
Requires-Dist: odoo14-addon-partner-statement
Requires-Dist: odoo<14.1dev,>=14.0a
